gracie_feeds_api/GracieAPIClassLoader.py
gracie_feeds_api/GracieAuth.py
gracie_feeds_api/GracieErrors.py
gracie_feeds_api/__init__.py
gracie_feeds_api/feeds_controllers_classes/__init__.py
gracie_feeds_api/feeds_controllers_classes/accessController.py
gracie_feeds_api/feeds_controllers_classes/alertRuleController.py
gracie_feeds_api/feeds_controllers_classes/alerterController.py
gracie_feeds_api/feeds_controllers_classes/bulkProcessingController.py
gracie_feeds_api/feeds_controllers_classes/countriesController.py
gracie_feeds_api/feeds_controllers_classes/dirwatchController.py
gracie_feeds_api/feeds_controllers_classes/engineAppInfoController.py
gracie_feeds_api/feeds_controllers_classes/entitiesController.py
gracie_feeds_api/feeds_controllers_classes/filtersController.py
gracie_feeds_api/feeds_controllers_classes/geoEntitiesController.py
gracie_feeds_api/feeds_controllers_classes/infoController.py
gracie_feeds_api/feeds_controllers_classes/invalidateController.py
gracie_feeds_api/feeds_controllers_classes/languageController.py
gracie_feeds_api/feeds_controllers_classes/performanceController.py
gracie_feeds_api/feeds_controllers_classes/persistController.py
gracie_feeds_api/feeds_controllers_classes/pipelineController.py
gracie_feeds_api/feeds_controllers_classes/playbookController.py
gracie_feeds_api/feeds_controllers_classes/processFilesTasksController.py
gracie_feeds_api/feeds_controllers_classes/processTextsTasksController.py
gracie_feeds_api/feeds_controllers_classes/projectsController.py
gracie_feeds_api/feeds_controllers_classes/skillsController.py
gracie_feeds_api/feeds_controllers_classes/skillsetsController.py
gracie_feeds_api/feeds_controllers_classes/taskTypesController.py
gracie_feeds_api/feeds_controllers_classes/tasksController.py
gracie_feeds_api/feeds_controllers_classes/topicsController.py
gracie_feeds_api/feeds_controllers_classes/typesController.py
gracie_feeds_api/feeds_controllers_classes/usersController.py
gracie_feeds_api-100.6.0.28.1704924532.dist-info/LICENSE.txt
gracie_feeds_api-100.6.0.28.1704924532.dist-info/METADATA
gracie_feeds_api-100.6.0.28.1704924532.dist-info/WHEEL
gracie_feeds_api-100.6.0.28.1704924532.dist-info/top_level.txt
gracie_feeds_api-100.6.0.28.1704924532.dist-info/zip-safe
gracie_feeds_api-100.6.0.28.1704924532.dist-info/RECORD
