Metadata-Version: 2.1
Name: gracie-feeds-api
Version: 100.6.0.28.1704924532
Summary: Gracie Feeds API python wrapper
Home-page: https://gracie-feeds-api-documentation.readthedocs.io
Download-URL: https://pypi.org/project/gracie-feeds-api/
Author: Darshan Gencarelle
Author-email: darshan.gencarelle@toposlabs.com
License: commercial
Classifier: Development Status :: 5 - Production/Stable
Classifier: Environment :: MacOS X
Classifier: Environment :: Win32 (MS Windows)
Classifier: Environment :: X11 Applications
Classifier: Intended Audience :: Developers
Classifier: License :: OSI Approved :: BSD License
Classifier: Operating System :: MacOS :: MacOS X
Classifier: Operating System :: Microsoft :: Windows
Classifier: Operating System :: POSIX :: Linux
Classifier: Programming Language :: Python :: 3
Classifier: Programming Language :: Python :: 3.3
Classifier: Programming Language :: Python :: 3.4
Classifier: Topic :: Software Development :: Libraries :: Python Modules
License-File: LICENSE.txt
Requires-Dist: future
Requires-Dist: requests
Requires-Dist: funcsigs
